payjpv2/__init__.py
payjpv2/api_client.py
payjpv2/api_response.py
payjpv2/configuration.py
payjpv2/exceptions.py
payjpv2/py.typed
payjpv2/rest.py
payjpv2/api/__init__.py
payjpv2/api/balances_api.py
payjpv2/api/checkout_sessions_api.py
payjpv2/api/customers_api.py
payjpv2/api/events_api.py
payjpv2/api/payment_flows_api.py
payjpv2/api/payment_method_configurations_api.py
payjpv2/api/payment_methods_api.py
payjpv2/api/payment_refunds_api.py
payjpv2/api/payment_transactions_api.py
payjpv2/api/prices_api.py
payjpv2/api/products_api.py
payjpv2/api/setup_flows_api.py
payjpv2/api/statements_api.py
payjpv2/api/tax_rates_api.py
payjpv2/api/terms_api.py
payjpv2/models/__init__.py
payjpv2/models/balance_list_response.py
payjpv2/models/balance_response.py
payjpv2/models/balance_state.py
payjpv2/models/balance_url_response.py
payjpv2/models/bank_info_response.py
payjpv2/models/capture_method.py
payjpv2/models/card_config_request.py
payjpv2/models/checkout_session_create_request.py
payjpv2/models/checkout_session_customer_details_address_response.py
payjpv2/models/checkout_session_customer_details_response.py
payjpv2/models/checkout_session_details_response.py
payjpv2/models/checkout_session_line_item_data_response.py
payjpv2/models/checkout_session_line_item_list_response.py
payjpv2/models/checkout_session_list_response.py
payjpv2/models/checkout_session_mode.py
payjpv2/models/checkout_session_payment_method_options_card_request.py
payjpv2/models/checkout_session_payment_method_options_request.py
payjpv2/models/checkout_session_status.py
payjpv2/models/checkout_session_submit_type.py
payjpv2/models/checkout_session_ui_mode.py
payjpv2/models/checkout_session_update_request.py
payjpv2/models/country.py
payjpv2/models/currency.py
payjpv2/models/customer_create_request.py
payjpv2/models/customer_creation.py
payjpv2/models/customer_list_response.py
payjpv2/models/customer_response.py
payjpv2/models/customer_update_request.py
payjpv2/models/display_preference_request.py
payjpv2-1.0.4.dist-info/LICENSE
payjpv2-1.0.4.dist-info/METADATA
payjpv2-1.0.4.dist-info/WHEEL
payjpv2-1.0.4.dist-info/top_level.txt
payjpv2-1.0.4.dist-info/RECORD
