Metadata-Version: 2.1
Name: payjpv2
Version: 1.0.4
Summary: PAY.JP Python SDK - A Python client library for PAY.JP v2 API
Home-page: https://github.com/payjp/payjpv2-python
Author: PAY.JP
Author-email: "PAY.JP" <support@pay.jp>
License: MIT
Project-URL: Homepage, https://github.com/payjp/payjpv2-python
Project-URL: Repository, https://github.com/payjp/payjpv2-python
Project-URL: Issues, https://github.com/payjp/payjpv2-python/issues
Keywords: payjp,payment,api,sdk,fintech
Classifier: Development Status :: 5 - Production/Stable
Classifier: Intended Audience :: Developers
Classifier: Programming Language :: Python :: 3
Classifier: Programming Language :: Python :: 3.8
Classifier: Programming Language :: Python :: 3.9
Classifier: Programming Language :: Python :: 3.10
Classifier: Programming Language :: Python :: 3.11
Classifier: Programming Language :: Python :: 3.12
Requires-Python: >=3.8
License-File: LICENSE
Requires-Dist: urllib3 <3.0.0,>=2.1.0
Requires-Dist: python-dateutil >=2.8.2
Requires-Dist: pydantic >=2
Requires-Dist: typing-extensions >=4.7.1
Provides-Extra: dev
Requires-Dist: pytest >=7.2.1 ; extra == 'dev'
Requires-Dist: pytest-cov >=2.8.1 ; extra == 'dev'
Requires-Dist: tox >=3.9.0 ; extra == 'dev'
Requires-Dist: flake8 >=4.0.0 ; extra == 'dev'
Requires-Dist: types-python-dateutil >=2.8.19.14 ; extra == 'dev'
Requires-Dist: mypy >=1.5 ; extra == 'dev'
Requires-Dist: ruff >=0.1.0 ; extra == 'dev'
